{"cameraMode":{"drawMode":0,"name":"Shaded","section":"Shading Mode"},"sceneLighting":true,"audioPlay":false,"sceneViewState":{"m_AlwaysRefresh":false,"showFog":true,"showSkybox":true,"showFlares":true,"showImageEffects":true,"showParticleSystems":true,"showVisualEffectGraphs":true,"m_FxEnabled":true},"in2DMode":false,"pivot":{"x":0.18447698652744294,"y":-24.92465591430664,"z":-2.5085573196411135},"rotation":{"x":0.0007060947827994823,"y":0.9431907534599304,"z":-0.33259162306785586,"w":0.0019586323760449888},"size":54.57371139526367,"orthographic":false}